file_download/__init__.py
file_download/download.py
file_download-1.4.dist-info/entry_points.txt
file_download-1.4.dist-info/METADATA
file_download-1.4.dist-info/WHEEL
file_download-1.4.dist-info/RECORD
